myqlm_simulators-1.10.2.dist-info/licenses/LICENSE
myqlm_simulators-1.10.2.dist-info/licenses/NOTICE
qat/pylinalg/__init__.py
qat/pylinalg/service.py
qat/pylinalg/simulator.py
qat/qpus/hook_pylinalg.py
qat/simulated_annealing/__init__.py
qat/simulated_annealing/service.py
myqlm_simulators-1.10.2.dist-info/METADATA
myqlm_simulators-1.10.2.dist-info/WHEEL
myqlm_simulators-1.10.2.dist-info/top_level.txt
myqlm_simulators-1.10.2.dist-info/RECORD
