Metadata-Version: 2.4
Name: myqlm-simulators
Version: 1.10.2
Summary: myQLM-simulators package
Home-page: https://atos.net/en/lp/myqlm
Author: Atos Quantum Lab
License: Atos myQLM EULA
Project-URL: Documentation, https://myqlm.github.io
Project-URL: Bug Tracker, https://github.com/myQLM/myqlm-issues/issues
Project-URL: Community, https://myqlmworkspace.slack.com
Project-URL: Source code, https://github.com/myQLM/myqlm-simulators
License-File: LICENSE
License-File: NOTICE
Requires-Dist: qat-core
Requires-Dist: qat-lang
Requires-Dist: qat-variational
Requires-Dist: numpy~=2.0
Dynamic: author
Dynamic: description
Dynamic: description-content-type
Dynamic: home-page
Dynamic: license
Dynamic: license-file
Dynamic: project-url
Dynamic: requires-dist
Dynamic: summary
